parquet/__init__.py
parquet/__main__.py
parquet/converted_types.py
parquet/encoding.py
parquet/parquet.thrift
parquet/schema.py
parquet/thrift_filetransport.py
parquet-1.3.dist-info/LICENSE
parquet-1.3.dist-info/METADATA
parquet-1.3.dist-info/WHEEL
parquet-1.3.dist-info/entry_points.txt
parquet-1.3.dist-info/top_level.txt
parquet-1.3.dist-info/RECORD
