Metadata-Version: 2.1
Name: parquet
Version: 1.3
Summary: Python support for Parquet file format
Home-page: https://github.com/jcrobak/parquet-python
Author: Joe Crobak
Author-email: joecrow@gmail.com
License: Apache License 2.0
Platform: UNKNOWN
Classifier: Development Status :: 3 - Alpha
Classifier: Intended Audience :: Developers
Classifier: Intended Audience :: System Administrators
Classifier: License :: OSI Approved :: Apache Software License
Classifier: Programming Language :: Python
Classifier: Programming Language :: Python :: 2
Classifier: Programming Language :: Python :: 3
Classifier: Programming Language :: Python :: 2.7
Classifier: Programming Language :: Python :: 3.6
Classifier: Programming Language :: Python :: 3.7
Classifier: Programming Language :: Python :: Implementation :: CPython
Classifier: Programming Language :: Python :: Implementation :: PyPy
Requires-Dist: thriftpy2
Requires-Dist: backports.csv ; python_version=="2.7"
Provides-Extra: snappy
Requires-Dist: python-snappy ; extra == 'snappy'
